multiformer/__init__.py
multiformer-0.0.1.dist-info/METADATA
multiformer-0.0.1.dist-info/WHEEL
multiformer-0.0.1.dist-info/entry_points.txt
multiformer-0.0.1.dist-info/top_level.txt
multiformer-0.0.1.dist-info/RECORD
